{
    "Place":"Tribe Cafe",
    "Location":[
        {"Address":"#253, Calle Aramburu entre Neptuno y Sam Miguel, Cayo Hueso",
        "Municipality":"Centro Habana",
        "Coordinates":"4JPG+W44"}
    ],
    "Classification":"Cafe",
    "Specialization":"Cocina mixta e infusiones",
    "Ownership":"Privado",
    "Schedule":[
        {"Opening":"08h00",
        "Closing":"17h00",
        "Days":["Lunes","Martes","Miercoles","Jueves","Viernes","Sabado","Domingo"]}
    ],
    "Ratings":[
        {"Tripadvisor":5.0,
        "Google Maps":5.0}
    ],
    "Reservations":false,
    "Delivery":[
        {"Service existence":false,
        "Delivery area":null}
    ],
    "Phone number":null,
    "Accounts or website":[
        {"Facebook":null},
        {"Instagram":"@t_r_i_b_e_cafe"},
        {"Website":"https://es.tribecaribecayohueso.com"},
        {"Email":null}
    ],
    "Payment":[
        {"Method":["Tarjeta de credito","Transferencia","Efectivo"],
        "Accepted currencies":["CUP","USD","EUR"]}
    ],
    "Capacity":25,
    "Parking service":false,
    "Wifi":true,
    "Smoking area":true,
    "Menu card":{
        "Starters":[
            {"Plate":"Cesta de panes con aderezo",
            "Price":850},
            {"Plate":"Ensalada de frutas",
            "Price":600},
            {"Plate":"Papas fritas",
            "Price":450}
        ],
        "Main course":[
            {"Plate":"Yogurt fresco con granola / frutas",
            "Price":500},
            {"Plate":"Sandwich de jamon y queso",
            "Price":1000},
            {"Plate":"Sandwich de atun",
            "Price":1200},
            {"Plate":"Sandwich de vegetales",
            "Price":700},
            {"Plate":"Sandwich de bacon y queso",
            "Price":1200},
            {"Plate":"Super ensaladas",
            "Price":700},
            {"Plate":"Huevos con tostadas y vegetales",
            "Price":1000},
            {"Plate":"Tacos de pollo",
            "Price":800},
            {"Plate":"Tacos de cerdo",
            "Price":1000}
        ],
        "Additionals":[
            {"Addition":"Chia",
            "Price":200},
            {"Addition":"Salchicha",
            "Price":400},
            {"Addition":"Jamon",
            "Price":250},
            {"Addition":"Queso fresco",
            "Price":450},
            {"Addition":"Queso Gouda",
            "Price":400},
            {"Addition":"Vegetales",
            "Price":350},
            {"Addition":"Salsas",
            "Price":350},
            {"Addition":"Atun",
            "Price":400},
            {"Addition":"Cerdo",
            "Price":700}
        ],
        "Siders":null,
        "Drinks":[
            {"Type":"Cafe Expresso",
            "Price":200},
            {"Type":"Cappuccino",
            "Price":400},
            {"Type":"Cafe Macchiato",
            "Price":250},
            {"Type":"Cafe americano",
            "Price":250},
            {"Type":"Latte",
            "Price":450},
            {"Type":"Frappuccino",
            "Price":500},
            {"Type":"Cafe Hawaian",
            "Price":400},
            {"Type":"Cafe Moccha",
            "Price":350},
            {"Type":"Cafe cortado",
            "Price":250},
            {"Type":"Cafe French Press",
            "Price":1000},
            {"Type":"Iced Latte",
            "Price":300},
            {"Type":"Chocolate caliente",
            "Price":350},
            {"Type":"Leche de soja",
            "Price":900},
            {"Type":"Te caliente / frio",
            "Price":200},
            {"Type":"Batido / Smoothie",
            "Price":550},
            {"Type":"Agua",
            "Price":290},
            {"Type":"Soda",
            "Price":300},
            {"Type":"Jugos naturales",
            "Price":500},
            {"Type":"Cerveza nacional",
            "Price":550},
            {"Type":"Cerveza importada",
            "Price":450},
            {"Type":"Leche de almendra",
            "Price":600},
            {"Type":"Leche de avena",
            "Price":400},
            {"Type":"Leche de coco",
            "Price":400}
        ],
        "Desserts":null,
        "Vegetarian options":[
            {"Option":"Cesta de panes con aderezo",
            "Classification":"Starters"},
            {"Option":"Ensalada de frutas",
            "Classification":"Starters"},
            {"Option":"Papas fritas",
            "Classification":"Starters"},
            {"Option":"Yogurt fresco con granola / frutas",
            "Classification":"Main course"},
            {"Option":"Sandwich de vegetales",
            "Classification":"Main course"},
            {"Option":"Super ensaladas",
            "Classification":"Main course"}
        ]
    }
}