{
    "Place":"Don Balbino's",
    "Location":[
        {"Address":"Calzada de San Miguel del Padron entre 8va y B",
        "Municipality":"San Miguel del Padron",
        "Coordinates":"4M35+2V5"}
    ],
    "Classification":"Bar-Cafeteria",
    "Specialization":"Cocina mixta",
    "Ownership":"Privado",
    "Schedule":[
        {"Opening":"08h30",
        "Closing":"23h00",
        "Days":["Lunes","Martes","Miercoles","Jueves","Viernes","Sabado","Domingo"]}
    ],
    "Ratings":[
        {"Tripadvisor":null,
        "Google Maps":1.0}
    ],
    "Reservations":true,
    "Delivery":[
        {"Service existence":false,
        "Delivery area":null}
    ],
    "Phone number":"50945157 / 59885510 / 76910592",
    "Accounts or website":[
        {"Facebook":"Jamoneria Don Balbino"},
        {"Instagram":"@don.balbino"},
        {"Website":null},
        {"Email":"clientes@carnicosdonbalbino.com"}
    ],
    "Payment":[
        {"Method":["Transferencia","Efectivo"],
        "Accepted currencies":["CUP","USD","EUR"]}
    ],
    "Capacity":50,
    "Parking service":true,
    "Wifi":false,
    "Smoking area":true,
    "Menu card":{
        "Starters":[
            {"Plate":"Bolitas de queso",
            "Price":950},
            {"Plate":"Croquetas especiales de la casa",
            "Price":1200},
            {"Plate":"Croquetas del dia",
            "Price":900},
            {"Plate":"Fajitas de pollo",
            "Price":1100},
            {"Plate":"Frituras de malanga",
            "Price":800},
            {"Plate":"Masas de cerdo",
            "Price":1500},
            {"Plate":"Papas fritas",
            "Price":850},
            {"Plate":"Tabla Don Balbino",
            "Price":3000},
            {"Plate":"Tabla de vegetales",
            "Price":1400},
            {"Plate":"Tacos de res",
            "Price":1500},
            {"Plate":"Tacos de cerdo",
            "Price":1400},
            {"Plate":"Tostones rellenos",
            "Price":900}
        ],
        "Main course":[
            {"Plate":"Hamburguesa Full Pork",
            "Price":800},
            {"Plate":"Hamburguesa Original Beef Balbino's",
            "Price":900},
            {"Plate":"Hamburguesa Pollo Crispy",
            "Price":850},
            {"Plate":"Pan con lechon criollo",
            "Price":850},
            {"Plate":"Sandwich Balbino's",
            "Price":1000},
            {"Plate":"Sandwich de atun",
            "Price":900},
            {"Plate":"Sandwich de pollo",
            "Price":850},
            {"Plate":"Sandwich de jamon y queso",
            "Price":750},
            {"Plate":"Sandwich cubano",
            "Price":950},
            {"Plate":"Arroz frito",
            "Price":1500},
            {"Plate":"Fabada",
            "Price":2900},
            {"Plate":"Pechuga de pollo grille",
            "Price":2200},
            {"Plate":"Pollo frito",
            "Price":1800},
            {"Plate":"Bistec de cerdo encebollado",
            "Price":2300},
            {"Plate":"Cerdo asado",
            "Price":2500},
            {"Plate":"Costillas de cerdo",
            "Price":2600},
            {"Plate":"Fricase de cerdo a la Habanera",
            "Price":2650},
            {"Plate":"Lomo ahumado",
            "Price":2700},
            {"Plate":"Masa de cerdo frita",
            "Price":2550},
            {"Plate":"Bistec de cerdo grille",
            "Price":2400},
            {"Plate":"Estofado de res",
            "Price":2700},
            {"Plate":"Punta de filete",
            "Price":2500},
            {"Plate":"Ropa vieja",
            "Price":2600},
            {"Plate":"Camaron grille",
            "Price":2400},
            {"Plate":"Enchilado de camaron",
            "Price":2800},
            {"Plate":"Enchilado de langosta",
            "Price":2800},
            {"Plate":"Langosta grille",
            "Price":2550},
            {"Plate":"Filete de pescado grille",
            "Price":2150},
            {"Plate":"Espaghettis Napolitanos",
            "Price":1000},
            {"Plate":"Espaghettis a la bolognesa",
            "Price":1200},
            {"Plate":"Espaghettis Don Balbino",
            "Price":1300},
            {"Plate":"Pizza Napolitana",
            "Price":1200}
        ],
        "Additionals":[
            {"Addition":"Queso Gouda",
            "Price":385},
            {"Addition":"Jamon barra",
            "Price":420},
            {"Addition":"Jamon pierna",
            "Price":440},
            {"Addition":"Jamon Serrano",
            "Price":660},
            {"Addition":"Bacon",
            "Price":495},
            {"Addition":"Chorizo",
            "Price":330},
            {"Addition":"Salsa bolognesa",
            "Price":660},
            {"Addition":"Atun",
            "Price":385},
            {"Addition":"Ropa vieja",
            "Price":460},
            {"Addition":"Vegetales",
            "Price":240},
            {"Addition":"Aceitunas",
            "Price":380},
            {"Addition":"Cebolla",
            "Price":240},
            {"Addition":"Aji pimiento",
            "Price":275},
            {"Addition":"Pina glaseada",
            "Price":240},
            {"Addition":"Huevos",
            "Price":275},
            {"Addition":"Camarones",
            "Price":750}
        ],
        "Siders":[
            {"Type":"Arroz blanco",
            "Price":200},
            {"Type":"Arroz moro",
            "Price":300},
            {"Type":"Ensalada de vegetales",
            "Price":500},
            {"Type":"Vegetales salteados",
            "Price":450},
            {"Type":"Vianda frita",
            "Price":300},
            {"Type":"Tostones",
            "Price":650},
            {"Type":"Vianda con mojo",
            "Price":650},
            {"Type":"Platano maduro frito",
            "Price":500}
        ],
        "Drinks":[
            {"Type":"Batido de helado",
            "Price":700},
            {"Type":"Cerveza dispensada",
            "Price":400},
            {"Type":"Cerveza Heineken",
            "Price":500},
            {"Type":"Cerveza importada",
            "Price":350},
            {"Type":"Cerveza nacional",
            "Price":350},
            {"Type":"Chelada",
            "Price":250},
            {"Type":"Michelada",
            "Price":300},
            {"Type":"Agua natural",
            "Price":250},
            {"Type":"Batido de frutas",
            "Price":550},
            {"Type":"Jugo natural de frutas",
            "Price":400},
            {"Type":"Jugo de lata",
            "Price":400},
            {"Type":"Malta importada",
            "Price":400},
            {"Type":"Malta Morena",
            "Price":250},
            {"Type":"Malta nacional",
            "Price":500},
            {"Type":"Malteada",
            "Price":300},
            {"Type":"Red Bull",
            "Price":250},
            {"Type":"Refresco importado",
            "Price":450},
            {"Type":"Refresco nacional",
            "Price":500},
            {"Type":"Tigon",
            "Price":350},
            {"Type":"Kermato",
            "Price":350}
        ],
        "Desserts":[
            {"Plate":"Suero de helado",
            "Price":930}
        ],
        "Vegetarian options":[
            {"Option":"Bolitas de queso",
            "Classification":"Starters"},
            {"Option":"Frituras de malanga",
            "Classification":"Starters"},
            {"Option":"Papas fritas",
            "Classification":"Starters"},
            {"Option":"Tabla de vegetales",
            "Classification":"Starters"},
            {"Option":"Espaghettis Napolitanos",
            "Classification":"Main course"},
            {"Option":"Pizza Napolitana",
            "Classification":"Main course"},
            {"Option":"Ensalada de vegetales",
            "Classification":"Siders"},
            {"Option":"Vegetales salteados",
            "Classification":"Siders"},
            {"Option":"Vianda frita",
            "Classification":"Siders"},
            {"Option":"Tostones",
            "Classification":"Siders"},
            {"Option":"Vianda con mojo",
            "Classification":"Siders"},
            {"Option":"Platano maduro frito",
            "Classification":"Siders"}
        ]
    }
}